bioio_ome_tiled_tiff/__init__.py
bioio_ome_tiled_tiff/py.typed
bioio_ome_tiled_tiff/reader.py
bioio_ome_tiled_tiff/reader_metadata.py
bioio_ome_tiled_tiff/utils.py
bioio_ome_tiled_tiff-1.3.0.dist-info/licenses/LICENSE
bioio_ome_tiled_tiff-1.3.0.dist-info/METADATA
bioio_ome_tiled_tiff-1.3.0.dist-info/WHEEL
bioio_ome_tiled_tiff-1.3.0.dist-info/entry_points.txt
bioio_ome_tiled_tiff-1.3.0.dist-info/top_level.txt
bioio_ome_tiled_tiff-1.3.0.dist-info/RECORD
